terracotta/__init__.py
terracotta/_version.py
terracotta/cache.py
terracotta/cog.py
terracotta/config.py
terracotta/exceptions.py
terracotta/expressions.py
terracotta/image.py
terracotta/logs.py
terracotta/profile.py
terracotta/xyz.py
terracotta/client/__init__.py
terracotta/client/flask_api.py
terracotta/client/static/README.md
terracotta/client/static/favicon.ico
terracotta/client/static/leaflet.css
terracotta/client/static/leaflet.js
terracotta/client/static/main.css
terracotta/client/static/main.js
terracotta/client/static/nouislider.min.css
terracotta/client/static/nouislider.min.js
terracotta/client/static/images/header.svg
terracotta/client/static/types/leaflet.d.ts
terracotta/client/static/types/main.d.ts
terracotta/client/static/types/no-ui-slider.d.ts
terracotta/client/templates/app.html
terracotta/cmaps/__init__.py
terracotta/cmaps/accent_r_rgb.npy
terracotta/cmaps/accent_rgb.npy
terracotta/cmaps/afmhot_r_rgb.npy
terracotta/cmaps/afmhot_rgb.npy
terracotta/cmaps/autumn_r_rgb.npy
terracotta/cmaps/autumn_rgb.npy
terracotta/cmaps/binary_r_rgb.npy
terracotta/cmaps/binary_rgb.npy
terracotta/cmaps/blues_r_rgb.npy
terracotta/cmaps/blues_rgb.npy
terracotta/cmaps/bone_r_rgb.npy
terracotta/cmaps/bone_rgb.npy
terracotta/cmaps/brbg_r_rgb.npy
terracotta/cmaps/brbg_rgb.npy
terracotta/cmaps/brg_r_rgb.npy
terracotta/cmaps/brg_rgb.npy
terracotta/cmaps/bugn_r_rgb.npy
terracotta/cmaps/bugn_rgb.npy
terracotta/cmaps/bupu_r_rgb.npy
terracotta/cmaps/bupu_rgb.npy
terracotta/cmaps/bwr_r_rgb.npy
terracotta/cmaps/bwr_rgb.npy
terracotta/cmaps/cividis_r_rgb.npy
terracotta/cmaps/cividis_rgb.npy
terracotta/cmaps/cmrmap_r_rgb.npy
terracotta/cmaps/cmrmap_rgb.npy
terracotta/cmaps/cool_r_rgb.npy
terracotta/cmaps/cool_rgb.npy
terracotta/cmaps/coolwarm_r_rgb.npy
terracotta/cmaps/coolwarm_rgb.npy
terracotta/cmaps/copper_r_rgb.npy
terracotta/cmaps/copper_rgb.npy
terracotta/cmaps/cubehelix_r_rgb.npy
terracotta/cmaps/cubehelix_rgb.npy
terracotta/cmaps/dark2_r_rgb.npy
terracotta-0.5.1.dist-info/LICENSE
terracotta-0.5.1.dist-info/METADATA
terracotta-0.5.1.dist-info/WHEEL
terracotta-0.5.1.dist-info/entry_points.txt
terracotta-0.5.1.dist-info/top_level.txt
terracotta-0.5.1.dist-info/RECORD
