Metadata-Version: 2.1
Name: terracotta
Version: 0.5.1
Summary: A modern XYZ tile server written in Python
Home-page: https://github.com/DHI-GRAS/terracotta
Author: Philip Graae
Author-email: phgr@dhigroup.com
License: UNKNOWN
Keywords: xyz tileserver rasterio cloud-optimized-geotiff serverless
Platform: UNKNOWN
Classifier: Development Status :: 4 - Beta
Classifier: Intended Audience :: End Users/Desktop
Classifier: Intended Audience :: Science/Research
Classifier: Intended Audience :: System Administrators
Classifier: Topic :: Software Development :: Build Tools
Classifier: License :: OSI Approved :: MIT License
Classifier: Programming Language :: Python :: 3.6
Classifier: Programming Language :: Python :: 3.7
Classifier: Framework :: Flask
Classifier: Operating System :: Microsoft :: Windows :: Windows 10
Classifier: Operating System :: MacOS :: MacOS X
Classifier: Operating System :: Unix
Classifier: Topic :: Internet :: WWW/HTTP :: HTTP Servers
Classifier: Topic :: Internet :: WWW/HTTP :: WSGI :: Application
Classifier: Topic :: Multimedia :: Graphics :: Viewers
Classifier: Topic :: Scientific/Engineering :: GIS
Requires-Python: >=3.6
Requires-Dist: apispec (>=1.0)
Requires-Dist: apispec-webframeworks
Requires-Dist: cachetools (>=3.1.0)
Requires-Dist: click
Requires-Dist: flask
Requires-Dist: flask-cors
Requires-Dist: marshmallow (>=3.0.0b12)
Requires-Dist: mercantile
Requires-Dist: numpy (>=1.15)
Requires-Dist: pillow
Requires-Dist: pyyaml (>=3.10)
Requires-Dist: shapely
Requires-Dist: rasterio (>=1.0)
Requires-Dist: toml
Requires-Dist: tqdm
Provides-Extra: docs
Requires-Dist: sphinx ; extra == 'docs'
Requires-Dist: sphinx-autodoc-typehints ; extra == 'docs'
Requires-Dist: sphinx-click ; extra == 'docs'
Requires-Dist: pymysql ; extra == 'docs'
Provides-Extra: recommended
Requires-Dist: colorlog ; extra == 'recommended'
Requires-Dist: crick ; extra == 'recommended'
Requires-Dist: pymysql ; extra == 'recommended'
Provides-Extra: test
Requires-Dist: pytest ; extra == 'test'
Requires-Dist: pytest-cov ; extra == 'test'
Requires-Dist: pytest-mypy ; extra == 'test'
Requires-Dist: pytest-flake8 ; extra == 'test'
Requires-Dist: pytest-benchmark ; extra == 'test'
Requires-Dist: attrs (>=17.4.0) ; extra == 'test'
Requires-Dist: codecov ; extra == 'test'
Requires-Dist: colorlog ; extra == 'test'
Requires-Dist: crick ; extra == 'test'
Requires-Dist: flake8 (<3.7) ; extra == 'test'
Requires-Dist: matplotlib ; extra == 'test'
Requires-Dist: moto ; extra == 'test'
Requires-Dist: pymysql ; extra == 'test'
